MANIFEST.in
README.rst
setup.cfg
setup.py
omniforms/__init__.py
omniforms/admin.py
omniforms/admin_forms.py
omniforms/admin_views.py
omniforms/forms.py
omniforms/models.py
omniforms.egg-info/PKG-INFO
omniforms.egg-info/SOURCES.txt
omniforms.egg-info/dependency_links.txt
omniforms.egg-info/requires.txt
omniforms.egg-info/top_level.txt
omniforms/migrations/0001_initial.py
omniforms/migrations/0002_omniformsaveinstancehandler.py
omniforms/migrations/0003_auto_20160609_1336.py
omniforms/migrations/0004_omnislugfield.py
omniforms/migrations/0005_omnifilefield.py
omniforms/migrations/0006_omniimagefield.py
omniforms/migrations/0007_auto_20160613_0729.py
omniforms/migrations/0008_omnidurationfield_omnigenericipaddressfield_omniuuidfield.py
omniforms/migrations/0009_auto_20160614_1723.py
omniforms/migrations/0010_auto_20160614_1740.py
omniforms/migrations/0011_auto_20160614_1845.py
omniforms/migrations/0012_auto_20160614_1933.py
omniforms/migrations/0013_auto_20160614_1937.py
omniforms/migrations/0014_auto_20160614_2032.py
omniforms/migrations/0015_auto_20160614_2035.py
omniforms/migrations/0016_auto_20160615_1206.py
omniforms/migrations/0017_auto_20160616_0440.py
omniforms/migrations/0018_auto_20180212_0853.py
omniforms/migrations/0019_auto_20180212_1100.py
omniforms/migrations/0020_omnichoicefield_omnimultiplechoicefield.py
omniforms/migrations/0021_email_handlers.py
omniforms/migrations/0022_omniforeignkeyfieldnew_omnimanytomanyfieldnew.py
omniforms/migrations/0023_copy_related_data.py
omniforms/migrations/0024_delete_old_related_models.py
omniforms/migrations/0025_rename_new_related_models.py
omniforms/migrations/__init__.py
omniforms/templates/admin/omniforms/base/change_form.html
omniforms/templates/admin/omniforms/base/field_form.html
omniforms/templates/admin/omniforms/base/handler_form.html
omniforms/templates/admin/omniforms/base/preview.html
omniforms/templates/admin/omniforms/base/related_form.html
omniforms/templates/admin/omniforms/base/selectfield_form.html
omniforms/templates/admin/omniforms/base/selecthandler_form.html
omniforms/templates/admin/omniforms/base/selectrelated_form.html
