Metadata-Version: 1.1
Name: omniforms
Version: 0.4.0
Summary: A simple Django app to build forms using the admin interface.
Home-page: https://github.com/omni-digital/omni-forms/
Author: Omni Digital
Author-email: dev@omni-digital.co.uk
License: MIT
Download-URL: https://github.com/omni-digital/omni-forms/tarball/0.4.0
Keywords: form builder,django,wagtail
Platform: UNKNOWN
Classifier: Environment :: Web Environment
Classifier: Framework :: Django
Classifier: Framework :: Django :: 1.11
Classifier: Intended Audience :: Developers
Classifier: License :: OSI Approved :: MIT License
Classifier: Operating System :: OS Independent
Classifier: Programming Language :: Python
Classifier: Programming Language :: Python :: 2
Classifier: Programming Language :: Python :: 2.7
Classifier: Programming Language :: Python :: 3
Classifier: Programming Language :: Python :: 3.4
Classifier: Programming Language :: Python :: 3.5
Classifier: Programming Language :: Python :: 3.6
Classifier: Topic :: Internet :: WWW/HTTP
Classifier: Topic :: Internet :: WWW/HTTP :: Dynamic Content
